{
    "best_index": 4,
    "best_params": {
        "mlp__alpha": 50,
        "mlp__hidden_layer_sizes": [
            90
        ]
    },
    "best_score": 0.733882874015748,
    "results": {
        "mean_fit_time": {
            "0": 70.0036831617,
            "1": 100.2155708551,
            "10": 113.224020648,
            "11": 111.1443550825,
            "12": 90.224237895,
            "13": 130.3627494335,
            "14": 137.0173943758,
            "15": 121.597393012,
            "16": 125.7643842936,
            "17": 121.06921103,
            "18": 91.1378460884,
            "19": 142.6778534412,
            "2": 111.1331285954,
            "20": 131.2013209105,
            "21": 126.2634437084,
            "22": 117.2084738255,
            "23": 97.3796793222,
            "3": 104.4954711199,
            "4": 102.3957485914,
            "5": 96.6369976044,
            "6": 86.2633183956,
            "7": 118.2725358725,
            "8": 114.6929218054,
            "9": 112.4435743809
        },
        "mean_score_time": {
            "0": 0.3340091228,
            "1": 0.3128513813,
            "10": 0.2212648392,
            "11": 0.2430432558,
            "12": 0.1953158617,
            "13": 0.2395557404,
            "14": 0.243420434,
            "15": 0.2358012915,
            "16": 0.2221889973,
            "17": 0.2469721556,
            "18": 0.208676672,
            "19": 0.2196790695,
            "2": 0.2745477676,
            "20": 0.2259091377,
            "21": 0.2343094587,
            "22": 0.1555339575,
            "23": 0.0797565937,
            "3": 0.2549378395,
            "4": 0.2183175087,
            "5": 0.2207925558,
            "6": 0.1892037392,
            "7": 0.2067243099,
            "8": 0.2396597385,
            "9": 0.2544205427
        },
        "mean_test_score": {
            "0": 0.5022145669,
            "1": 0.7161663386,
            "10": 0.6003937008,
            "11": 0.608636811,
            "12": 0.1600639764,
            "13": 0.4100639764,
            "14": 0.437007874,
            "15": 0.4608759843,
            "16": 0.4564468504,
            "17": 0.4778543307,
            "18": 0.0880905512,
            "19": 0.3307086614,
            "2": 0.7205954724,
            "20": 0.3537155512,
            "21": 0.357898622,
            "22": 0.3619586614,
            "23": 0.3784448819,
            "3": 0.7327755906,
            "4": 0.733882874,
            "5": 0.7335137795,
            "6": 0.2957677165,
            "7": 0.5584399606,
            "8": 0.578371063,
            "9": 0.5859990157
        },
        "mean_train_score": {
            "0": 0.5164763057,
            "1": 0.7356723349,
            "10": 0.6083702268,
            "11": 0.6157275678,
            "12": 0.1600230721,
            "13": 0.4153766214,
            "14": 0.4445619885,
            "15": 0.4638900738,
            "16": 0.4635987919,
            "17": 0.47979516,
            "18": 0.0874848459,
            "19": 0.3329931914,
            "2": 0.7435822155,
            "20": 0.3516751143,
            "21": 0.3632932761,
            "22": 0.3656886943,
            "23": 0.3793713472,
            "3": 0.7509059014,
            "4": 0.7569683455,
            "5": 0.7581411391,
            "6": 0.295663859,
            "7": 0.5640406785,
            "8": 0.588792375,
            "9": 0.5977991927
        },
        "param_mlp__alpha": {
            "0": 50,
            "1": 50,
            "10": 100,
            "11": 100,
            "12": 150,
            "13": 150,
            "14": 150,
            "15": 150,
            "16": 150,
            "17": 150,
            "18": 200,
            "19": 200,
            "2": 50,
            "20": 200,
            "21": 200,
            "22": 200,
            "23": 200,
            "3": 50,
            "4": 50,
            "5": 50,
            "6": 100,
            "7": 100,
            "8": 100,
            "9": 100
        },
        "param_mlp__hidden_layer_sizes": {
            "0": [
                10
            ],
            "1": [
                50
            ],
            "10": [
                90
            ],
            "11": [
                100
            ],
            "12": [
                10
            ],
            "13": [
                50
            ],
            "14": [
                70
            ],
            "15": [
                80
            ],
            "16": [
                90
            ],
            "17": [
                100
            ],
            "18": [
                10
            ],
            "19": [
                50
            ],
            "2": [
                70
            ],
            "20": [
                70
            ],
            "21": [
                80
            ],
            "22": [
                90
            ],
            "23": [
                100
            ],
            "3": [
                80
            ],
            "4": [
                90
            ],
            "5": [
                100
            ],
            "6": [
                10
            ],
            "7": [
                50
            ],
            "8": [
                70
            ],
            "9": [
                80
            ]
        },
        "params": {
            "0": {
                "mlp__alpha": 50,
                "mlp__hidden_layer_sizes": [
                    10
                ]
            },
            "1": {
                "mlp__alpha": 50,
                "mlp__hidden_layer_sizes": [
                    50
                ]
            },
            "10": {
                "mlp__alpha": 100,
                "mlp__hidden_layer_sizes": [
                    90
                ]
            },
            "11": {
                "mlp__alpha": 100,
                "mlp__hidden_layer_sizes": [
                    100
                ]
            },
            "12": {
                "mlp__alpha": 150,
                "mlp__hidden_layer_sizes": [
                    10
                ]
            },
            "13": {
                "mlp__alpha": 150,
                "mlp__hidden_layer_sizes": [
                    50
                ]
            },
            "14": {
                "mlp__alpha": 150,
                "mlp__hidden_layer_sizes": [
                    70
                ]
            },
            "15": {
                "mlp__alpha": 150,
                "mlp__hidden_layer_sizes": [
                    80
                ]
            },
            "16": {
                "mlp__alpha": 150,
                "mlp__hidden_layer_sizes": [
                    90
                ]
            },
            "17": {
                "mlp__alpha": 150,
                "mlp__hidden_layer_sizes": [
                    100
                ]
            },
            "18": {
                "mlp__alpha": 200,
                "mlp__hidden_layer_sizes": [
                    10
                ]
            },
            "19": {
                "mlp__alpha": 200,
                "mlp__hidden_layer_sizes": [
                    50
                ]
            },
            "2": {
                "mlp__alpha": 50,
                "mlp__hidden_layer_sizes": [
                    70
                ]
            },
            "20": {
                "mlp__alpha": 200,
                "mlp__hidden_layer_sizes": [
                    70
                ]
            },
            "21": {
                "mlp__alpha": 200,
                "mlp__hidden_layer_sizes": [
                    80
                ]
            },
            "22": {
                "mlp__alpha": 200,
                "mlp__hidden_layer_sizes": [
                    90
                ]
            },
            "23": {
                "mlp__alpha": 200,
                "mlp__hidden_layer_sizes": [
                    100
                ]
            },
            "3": {
                "mlp__alpha": 50,
                "mlp__hidden_layer_sizes": [
                    80
                ]
            },
            "4": {
                "mlp__alpha": 50,
                "mlp__hidden_layer_sizes": [
                    90
                ]
            },
            "5": {
                "mlp__alpha": 50,
                "mlp__hidden_layer_sizes": [
                    100
                ]
            },
            "6": {
                "mlp__alpha": 100,
                "mlp__hidden_layer_sizes": [
                    10
                ]
            },
            "7": {
                "mlp__alpha": 100,
                "mlp__hidden_layer_sizes": [
                    50
                ]
            },
            "8": {
                "mlp__alpha": 100,
                "mlp__hidden_layer_sizes": [
                    70
                ]
            },
            "9": {
                "mlp__alpha": 100,
                "mlp__hidden_layer_sizes": [
                    80
                ]
            }
        },
        "rank_test_score": {
            "0": 11,
            "1": 5,
            "10": 7,
            "11": 6,
            "12": 23,
            "13": 16,
            "14": 15,
            "15": 13,
            "16": 14,
            "17": 12,
            "18": 24,
            "19": 21,
            "2": 4,
            "20": 20,
            "21": 19,
            "22": 18,
            "23": 17,
            "3": 3,
            "4": 1,
            "5": 2,
            "6": 22,
            "7": 10,
            "8": 9,
            "9": 8
        },
        "split0_test_score": {
            "0": 0.4963592233,
            "1": 0.7269417476,
            "10": 0.5970873786,
            "11": 0.6080097087,
            "12": 0.1953883495,
            "13": 0.4174757282,
            "14": 0.4538834951,
            "15": 0.463592233,
            "16": 0.4611650485,
            "17": 0.484223301,
            "18": 0.0716019417,
            "19": 0.338592233,
            "2": 0.729368932,
            "20": 0.3531553398,
            "21": 0.359223301,
            "22": 0.3555825243,
            "23": 0.3834951456,
            "3": 0.7233009709,
            "4": 0.7415048544,
            "5": 0.7463592233,
            "6": 0.2439320388,
            "7": 0.5388349515,
            "8": 0.5716019417,
            "9": 0.588592233
        },
        "split0_train_score": {
            "0": 0.5005476451,
            "1": 0.7322015334,
            "10": 0.6043263965,
            "11": 0.5966593647,
            "12": 0.1934556407,
            "13": 0.4140197152,
            "14": 0.443592552,
            "15": 0.4618017525,
            "16": 0.4500273823,
            "17": 0.4769989047,
            "18": 0.0636637459,
            "19": 0.3385815991,
            "2": 0.7390470975,
            "20": 0.3515881709,
            "21": 0.3628148959,
            "22": 0.3541894852,
            "23": 0.3885542169,
            "3": 0.7365826944,
            "4": 0.7495892662,
            "5": 0.7573932092,
            "6": 0.2348028478,
            "7": 0.5492880613,
            "8": 0.5779025192,
            "9": 0.598713034
        },
        "split1_test_score": {
            "0": 0.5279126214,
            "1": 0.7245145631,
            "10": 0.5958737864,
            "11": 0.6116504854,
            "12": 0.1589805825,
            "13": 0.3992718447,
            "14": 0.4126213592,
            "15": 0.4563106796,
            "16": 0.4356796117,
            "17": 0.4757281553,
            "18": 0.0813106796,
            "19": 0.3203883495,
            "2": 0.713592233,
            "20": 0.3252427184,
            "21": 0.3276699029,
            "22": 0.3604368932,
            "23": 0.3701456311,
            "3": 0.7354368932,
            "4": 0.7463592233,
            "5": 0.7330097087,
            "6": 0.3410194175,
            "7": 0.5655339806,
            "8": 0.5861650485,
            "9": 0.6080097087
        },
        "split1_train_score": {
            "0": 0.5161555312,
            "1": 0.7278203724,
            "10": 0.5865279299,
            "11": 0.6072015334,
            "12": 0.1588170865,
            "13": 0.4127875137,
            "14": 0.4320920044,
            "15": 0.4511226725,
            "16": 0.4403066813,
            "17": 0.4783680175,
            "18": 0.0843373494,
            "19": 0.3331051479,
            "2": 0.7311062432,
            "20": 0.3422782037,
            "21": 0.3513143483,
            "22": 0.3667853231,
            "23": 0.3725355969,
            "3": 0.7458926616,
            "4": 0.7598576123,
            "5": 0.7498630887,
            "6": 0.3532311062,
            "7": 0.5621577218,
            "8": 0.5881708653,
            "9": 0.6007667032
        },
        "split2_test_score": {
            "0": 0.4695121951,
            "1": 0.7231707317,
            "10": 0.6048780488,
            "11": 0.6268292683,
            "12": 0.1804878049,
            "13": 0.3731707317,
            "14": 0.4219512195,
            "15": 0.4548780488,
            "16": 0.4451219512,
            "17": 0.4695121951,
            "18": 0.0963414634,
            "19": 0.3231707317,
            "2": 0.7329268293,
            "20": 0.3536585366,
            "21": 0.3353658537,
            "22": 0.3536585366,
            "23": 0.3573170732,
            "3": 0.7365853659,
            "4": 0.7512195122,
            "5": 0.7353658537,
            "6": 0.2609756098,
            "7": 0.5463414634,
            "8": 0.5792682927,
            "9": 0.6012195122
        },
        "split2_train_score": {
            "0": 0.4904214559,
            "1": 0.7389162562,
            "10": 0.6148056924,
            "11": 0.6172687466,
            "12": 0.1735084839,
            "13": 0.39969896,
            "14": 0.4422550629,
            "15": 0.4541598248,
            "16": 0.4559386973,
            "17": 0.4735905857,
            "18": 0.0994800219,
            "19": 0.3322386426,
            "2": 0.7428845101,
            "20": 0.3512588944,
            "21": 0.3487958402,
            "22": 0.3732895457,
            "23": 0.3627531472,
            "3": 0.7448002189,
            "4": 0.7528735632,
            "5": 0.7491789819,
            "6": 0.2764094143,
            "7": 0.5621237001,
            "8": 0.5893541325,
            "9": 0.6071428571
        },
        "split3_test_score": {
            "0": 0.5,
            "1": 0.7243902439,
            "10": 0.6036585366,
            "11": 0.6207317073,
            "12": 0.1768292683,
            "13": 0.4097560976,
            "14": 0.4304878049,
            "15": 0.4573170732,
            "16": 0.4451219512,
            "17": 0.4963414634,
            "18": 0.0768292683,
            "19": 0.3231707317,
            "2": 0.7463414634,
            "20": 0.3634146341,
            "21": 0.3890243902,
            "22": 0.3865853659,
            "23": 0.3756097561,
            "3": 0.743902439,
            "4": 0.7451219512,
            "5": 0.737804878,
            "6": 0.3280487805,
            "7": 0.5670731707,
            "8": 0.5768292683,
            "9": 0.5841463415
        },
        "split3_train_score": {
            "0": 0.5143678161,
            "1": 0.7391899288,
            "10": 0.6020799124,
            "11": 0.6245210728,
            "12": 0.1804871374,
            "13": 0.4180350301,
            "14": 0.4359605911,
            "15": 0.4631910235,
            "16": 0.4579912425,
            "17": 0.4922003284,
            "18": 0.0769020252,
            "19": 0.3245758073,
            "2": 0.7471264368,
            "20": 0.3446907499,
            "21": 0.3657635468,
            "22": 0.3706896552,
            "23": 0.3779419814,
            "3": 0.7409688013,
            "4": 0.7625889436,
            "5": 0.7480842912,
            "6": 0.3238916256,
            "7": 0.5669129721,
            "8": 0.5733442802,
            "9": 0.5987958402
        },
        "split4_test_score": {
            "0": 0.5363748459,
            "1": 0.7299630086,
            "10": 0.6189889026,
            "11": 0.643649815,
            "12": 0.1689272503,
            "13": 0.421701603,
            "14": 0.4648581998,
            "15": 0.4821208385,
            "16": 0.4858199753,
            "17": 0.4821208385,
            "18": 0.1011097411,
            "19": 0.3600493218,
            "2": 0.728729963,
            "20": 0.3440197287,
            "21": 0.3600493218,
            "22": 0.3674475956,
            "23": 0.3908754624,
            "3": 0.7546239211,
            "4": 0.7410604192,
            "5": 0.7521578298,
            "6": 0.336621455,
            "7": 0.5832305795,
            "8": 0.5906288533,
            "9": 0.6226880395
        },
        "split4_train_score": {
            "0": 0.5213885472,
            "1": 0.733770671,
            "10": 0.6115894492,
            "11": 0.6329096624,
            "12": 0.180401804,
            "13": 0.3992073254,
            "14": 0.4473144731,
            "15": 0.4552412191,
            "16": 0.4638513052,
            "17": 0.4618012847,
            "18": 0.1072844062,
            "19": 0.3412600793,
            "2": 0.7199671997,
            "20": 0.3416700834,
            "21": 0.3520568539,
            "22": 0.3547902146,
            "23": 0.3798004647,
            "3": 0.7508541752,
            "4": 0.7408774088,
            "5": 0.7611042777,
            "6": 0.3173431734,
            "7": 0.5659423261,
            "8": 0.5733223999,
            "9": 0.6070794041
        },
        "split5_test_score": {
            "0": 0.4932182491,
            "1": 0.7324290999,
            "10": 0.5955610358,
            "11": 0.6029593095,
            "12": 0.1171393342,
            "13": 0.4106041924,
            "14": 0.4377311961,
            "15": 0.4660912454,
            "16": 0.4611590629,
            "17": 0.477188656,
            "18": 0.0863131936,
            "19": 0.3403205919,
            "2": 0.7509247842,
            "20": 0.3723797781,
            "21": 0.3649815043,
            "22": 0.3489519112,
            "23": 0.3797780518,
            "3": 0.748458693,
            "4": 0.7373612824,
            "5": 0.758323058,
            "6": 0.2996300863,
            "7": 0.5721331689,
            "8": 0.5770653514,
            "9": 0.5684340321
        },
        "split5_train_score": {
            "0": 0.5086784201,
            "1": 0.7359573596,
            "10": 0.6018860189,
            "11": 0.623069564,
            "12": 0.1091977586,
            "13": 0.409867432,
            "14": 0.4463577969,
            "15": 0.4874948749,
            "16": 0.4816181495,
            "17": 0.491868252,
            "18": 0.0854175208,
            "19": 0.3415334153,
            "2": 0.7432007653,
            "20": 0.3672270056,
            "21": 0.3804838048,
            "22": 0.368730354,
            "23": 0.3819871532,
            "3": 0.7441574416,
            "4": 0.7479841465,
            "5": 0.7570042367,
            "6": 0.2968429684,
            "7": 0.5711357114,
            "8": 0.5909525762,
            "9": 0.5876725434
        },
        "split6_test_score": {
            "0": 0.5427509294,
            "1": 0.7596034696,
            "10": 0.6332094176,
            "11": 0.6332094176,
            "12": 0.1573729864,
            "13": 0.4349442379,
            "14": 0.43866171,
            "15": 0.4671623296,
            "16": 0.4560099133,
            "17": 0.4894671623,
            "18": 0.1003717472,
            "19": 0.3345724907,
            "2": 0.7534076828,
            "20": 0.3705080545,
            "21": 0.3705080545,
            "22": 0.3680297398,
            "23": 0.3940520446,
            "3": 0.770755886,
            "4": 0.7732342007,
            "5": 0.7633209418,
            "6": 0.3519206939,
            "7": 0.5762081784,
            "8": 0.5774473358,
            "9": 0.604708798
        },
        "split6_train_score": {
            "0": 0.5329872968,
            "1": 0.7354186587,
            "10": 0.621090015,
            "11": 0.6008741975,
            "12": 0.1546236853,
            "13": 0.425761508,
            "14": 0.4410599645,
            "15": 0.45185084,
            "16": 0.4660565497,
            "17": 0.4842234667,
            "18": 0.0945226062,
            "19": 0.3349269226,
            "2": 0.7403360197,
            "20": 0.3489960388,
            "21": 0.3708509766,
            "22": 0.3582843874,
            "23": 0.3798661385,
            "3": 0.7477120612,
            "4": 0.7645130447,
            "5": 0.7608250239,
            "6": 0.3423029641,
            "7": 0.5667258571,
            "8": 0.5704138779,
            "9": 0.5922688157
        },
        "split7_test_score": {
            "0": 0.4944237918,
            "1": 0.7100371747,
            "10": 0.6121437423,
            "11": 0.6034696406,
            "12": 0.1511771995,
            "13": 0.4324659232,
            "14": 0.4535315985,
            "15": 0.448574969,
            "16": 0.4671623296,
            "17": 0.4758364312,
            "18": 0.102850062,
            "19": 0.3159851301,
            "2": 0.7050805452,
            "20": 0.3568773234,
            "21": 0.3568773234,
            "22": 0.3395291202,
            "23": 0.3804213135,
            "3": 0.7273853779,
            "4": 0.7249070632,
            "5": 0.7298636927,
            "6": 0.2503097893,
            "7": 0.5551425031,
            "8": 0.5885997522,
            "9": 0.5737298637
        },
        "split7_train_score": {
            "0": 0.5329872968,
            "1": 0.7448436006,
            "10": 0.614670127,
            "11": 0.611255293,
            "12": 0.1577653326,
            "13": 0.4343668898,
            "14": 0.4579975413,
            "15": 0.4492555662,
            "16": 0.4739789646,
            "17": 0.4773937987,
            "18": 0.1003961207,
            "19": 0.3323316487,
            "2": 0.7598688704,
            "20": 0.3603332878,
            "21": 0.3690752629,
            "22": 0.3595137276,
            "23": 0.3825980057,
            "3": 0.7628739243,
            "4": 0.7585029368,
            "5": 0.7684742522,
            "6": 0.2705914493,
            "7": 0.5556617948,
            "8": 0.603332878,
            "9": 0.5918590357
        },
        "split8_test_score": {
            "0": 0.4738154613,
            "1": 0.6645885287,
            "10": 0.5735660848,
            "11": 0.5673316708,
            "12": 0.150872818,
            "13": 0.3927680798,
            "14": 0.4251870324,
            "15": 0.4526184539,
            "16": 0.4488778055,
            "17": 0.4538653367,
            "18": 0.0685785536,
            "19": 0.325436409,
            "2": 0.6820448878,
            "20": 0.3416458853,
            "21": 0.3379052369,
            "22": 0.3578553616,
            "23": 0.3753117207,
            "3": 0.6882793017,
            "4": 0.6957605985,
            "5": 0.687032419,
            "6": 0.2556109726,
            "7": 0.5349127182,
            "8": 0.5760598504,
            "9": 0.5473815461
        },
        "split8_train_score": {
            "0": 0.5218400218,
            "1": 0.7373737374,
            "10": 0.613977614,
            "11": 0.6240786241,
            "12": 0.1438711439,
            "13": 0.4174174174,
            "14": 0.4520884521,
            "15": 0.4784329784,
            "16": 0.4657384657,
            "17": 0.4696969697,
            "18": 0.0705705706,
            "19": 0.3262353262,
            "2": 0.7644007644,
            "20": 0.3577668578,
            "21": 0.3697788698,
            "22": 0.3817908818,
            "23": 0.3909363909,
            "3": 0.7663117663,
            "4": 0.7689052689,
            "5": 0.7619437619,
            "6": 0.2590772591,
            "7": 0.5694785695,
            "8": 0.6149331149,
            "9": 0.5967785968
        },
        "split9_test_score": {
            "0": 0.4875311721,
            "1": 0.6645885287,
            "10": 0.5685785536,
            "11": 0.5673316708,
            "12": 0.1421446384,
            "13": 0.4089775561,
            "14": 0.4314214464,
            "15": 0.4600997506,
            "16": 0.4588528678,
            "17": 0.4738154613,
            "18": 0.0960099751,
            "19": 0.325436409,
            "2": 0.6620947631,
            "20": 0.3566084788,
            "21": 0.3778054863,
            "22": 0.3815461347,
            "23": 0.3778054863,
            "3": 0.6982543641,
            "4": 0.680798005,
            "5": 0.6907730673,
            "6": 0.289276808,
            "7": 0.5448877805,
            "8": 0.5598503741,
            "9": 0.5598503741
        },
        "split9_train_score": {
            "0": 0.5253890254,
            "1": 0.7312312312,
            "10": 0.6127491127,
            "11": 0.6194376194,
            "12": 0.1481026481,
            "13": 0.4226044226,
            "14": 0.4469014469,
            "15": 0.4863499863,
            "16": 0.4804804805,
            "17": 0.4918099918,
            "18": 0.0922740923,
            "19": 0.3251433251,
            "2": 0.7478842479,
            "20": 0.3509418509,
            "21": 0.361998362,
            "22": 0.3688233688,
            "23": 0.3767403767,
            "3": 0.7689052689,
            "4": 0.763991264,
            "5": 0.7675402675,
            "6": 0.2821457821,
            "7": 0.570980071,
            "8": 0.6061971062,
            "9": 0.5969150969
        },
        "std_fit_time": {
            "0": 11.1759974046,
            "1": 7.4731184021,
            "10": 11.8694404147,
            "11": 10.8818931408,
            "12": 5.2289824603,
            "13": 11.1249963382,
            "14": 7.8470630313,
            "15": 9.8210123862,
            "16": 11.0798498152,
            "17": 12.7062864948,
            "18": 5.3522589004,
            "19": 11.8090830429,
            "2": 11.2798813376,
            "20": 9.3354654961,
            "21": 11.3363178351,
            "22": 7.8119991524,
            "23": 16.2522999772,
            "3": 9.1188202119,
            "4": 8.061647794,
            "5": 12.4319690335,
            "6": 7.8253398923,
            "7": 10.9753095225,
            "8": 11.0438638122,
            "9": 6.8350833476
        },
        "std_score_time": {
            "0": 0.0684204993,
            "1": 0.0660658998,
            "10": 0.0352120725,
            "11": 0.0641357072,
            "12": 0.0217065361,
            "13": 0.0712686744,
            "14": 0.0394020817,
            "15": 0.0448308305,
            "16": 0.0276237867,
            "17": 0.0527631634,
            "18": 0.0223753569,
            "19": 0.0249408925,
            "2": 0.0551315964,
            "20": 0.0470814359,
            "21": 0.0622216992,
            "22": 0.0450764616,
            "23": 0.0496867187,
            "3": 0.0643731349,
            "4": 0.0620107473,
            "5": 0.0528233661,
            "6": 0.0419178476,
            "7": 0.0499236435,
            "8": 0.0540902778,
            "9": 0.029304041
        },
        "std_test_score": {
            "0": 0.0239446713,
            "1": 0.0281431566,
            "10": 0.0182929776,
            "11": 0.0239569341,
            "12": 0.0209122173,
            "13": 0.0175831451,
            "14": 0.0154276422,
            "15": 0.0090139365,
            "16": 0.013334266,
            "17": 0.0109598324,
            "18": 0.012225794,
            "19": 0.0123357051,
            "2": 0.028434063,
            "20": 0.0134178365,
            "21": 0.0184845242,
            "22": 0.0136200172,
            "23": 0.0098279951,
            "3": 0.0235584122,
            "4": 0.0255790069,
            "5": 0.0244544509,
            "6": 0.0394558827,
            "7": 0.0158602843,
            "8": 0.0084339985,
            "9": 0.0224260264
        },
        "std_train_score": {
            "0": 0.0129440908,
            "1": 0.0045506975,
            "10": 0.009375123,
            "11": 0.0109052664,
            "12": 0.022705864,
            "13": 0.0103830646,
            "14": 0.0070812875,
            "15": 0.0140341693,
            "16": 0.0124295874,
            "17": 0.0097133202,
            "18": 0.0132468448,
            "19": 0.0059616062,
            "2": 0.0121441028,
            "20": 0.0077396025,
            "21": 0.0095711172,
            "22": 0.008404202,
            "23": 0.0075340242,
            "3": 0.0106141821,
            "4": 0.0083778285,
            "5": 0.0069094046,
            "6": 0.0360307141,
            "7": 0.006649869,
            "8": 0.014619779,
            "9": 0.0059523417
        }
    }
}